Workbook
Name Slicer_Country_Name: #N/A
Name Slicer_Series_Name: #N/A

Sheet RawData
A1: Country Name | B1: Series Name | C1: 2015 [YR2015] | D1: 2016 [YR2016] | E1: 2017 [YR2017] | F1: 2018 [YR2018] | G1: 2019 [YR2019] | H1: 2020 [YR2020] | I1: 2021 [YR2021] | J1: 2022 [YR2022] | K1: 2023 [YR2023]
A2: Nigeria | B2: Unemployment, youth total (% of total labor force ages 15-24) (modeled ILO estimate) | C2: 8.457 | D2: 9.1 | E2: 9.707 | F2: 10.138 | G2: 10.418 | H2: 10.842 | I2: 8.991 | J2: 6.024 | K2: 5.131
A3: Nigeria | B3: Individuals using the Internet (% of population) | C3: 22.5142 | D3: 24.137501 | E3: 25.877899 | F3: 27.7437 | G3: 29.744101 | H3: 31.8888 | I3: 35.5098 | J3: 39.147202 | K3: 40.063999
A4: Malawi | B4: Unemployment, youth total (% of total labor force ages 15-24) (modeled ILO estimate) | C4: 6.75 | D4: 6.819 | E4: 6.865 | F4: 6.853 | G4: 6.812 | H4: 7.831 | I4: 7.632 | J4: 6.848 | K4: 6.842
A5: Malawi | B5: Individuals using the Internet (% of population) | C5: 6 | D5: 6.3000002 | E5: 7 | F5: 8.7982998 | G5: 11.0586 | H5: 13.8995 | I5: 15.303 | J5: 16.848301 | K5: 17.988103
A6: Mozambique | B6: Unemployment, youth total (% of total labor force ages 15-24) (modeled ILO estimate) | C6: 7.097 | D6: 7.401 | E6: 7.798 | F6: 8.173 | G6: 8.511 | H6: 9.707 | I6: 9.836 | J6: 11.619 | K6: 11.471
A7: Mozambique | B7: Individuals using the Internet (% of population) | C7: 6.5 | D7: 7 | E7: 7.7963266 | F7: 10.9 | G7: 12.4793 | H7: 14.2874 | I7: 16.357599 | J7: 18.9622 | K7: 19.945601
A8: Kenya | B8: Unemployment, youth total (% of total labor force ages 15-24) (modeled ILO estimate) | C8: 7.299 | D8: 7.333 | E8: 9.097 | F8: 10.818 | G8: 12.547 | H8: 13.619 | I8: 12.232 | J8: 15.488 | K8: 15.164
A9: Kenya | B9: Individuals using the Internet (% of population) | C9: 16.587855 | D9: 16.6 | E9: 17.827101 | F9: 19.5 | G9: 22.668773 | H9: 24.722799 | I9: 26.9629 | J9: 29.405899 | K9: 32.0704
A10: Rwanda | B10: Unemployment, youth total (% of total labor force ages 15-24) (modeled ILO estimate) | C10: 16.599 | D10: 16.595 | E10: 16.732 | F10: 16.264 | G10: 16.052 | H10: 15.947 | I10: 23.312 | J10: 22.203 | K10: 18.172
A11: Rwanda | B11: Individuals using the Internet (% of population) | C11: 12.456 | D11: 14.6371 | E11: 17.2 | F11: 19.166599 | G11: 21.358 | H11: 23.8 | I11: 24.441601 | J11: 28.0168 | K11: 28.805799
A12: Ghana | B12: Unemployment, youth total (% of total labor force ages 15-24) (modeled ILO estimate) | C12: 14.238 | D12: 10.616 | E12: 6.375 | F12: 6.107 | G12: 5.875 | H12: 6.319 | I12: 5.985 | J12: 5.402 | K12: 5.352
A13: Ghana | B13: Individuals using the Internet (% of population) | C13: 23 | D13: 28 | E13: 37.884201 | F13: 43 | G13: 22.0732 | H13: 62.517601 | I13: 68.6 | J13: 69.9133 | K13: 70.674301
... A29: Cote d'Ivoire | B29: Individuals using the Internet (% of population) | C29: 38.44 | D29: 41.207815 | E29: 43.839921 | F29: 37.546536 | G29: 36.288955 | H29: 36.016602 | I29: 35.950699 | J29: 38.413281 | K29: 40.65285
A33: Data from database: World Development Indicators
A34: Last Updated: 07/13/2026

Sheet MasterCharts
A1: Country Name | B1: Series Name | C1: Attribute | D1: Value
A2: Nigeria | B2: Unemployment, youth total (% of total labor force ages 15-24) (modeled ILO estimate) | C2: 2015 [YR2015] | D2: 8.457
A3: Nigeria | B3: Unemployment, youth total (% of total labor force ages 15-24) (modeled ILO estimate) | C3: 2016 [YR2016] | D3: 9.1
A4: Nigeria | B4: Unemployment, youth total (% of total labor force ages 15-24) (modeled ILO estimate) | C4: 2017 [YR2017] | D4: 9.707
A5: Nigeria | B5: Unemployment, youth total (% of total labor force ages 15-24) (modeled ILO estimate) | C5: 2018 [YR2018] | D5: 10.138
A6: Nigeria | B6: Unemployment, youth total (% of total labor force ages 15-24) (modeled ILO estimate) | C6: 2019 [YR2019] | D6: 10.418
A7: Nigeria | B7: Unemployment, youth total (% of total labor force ages 15-24) (modeled ILO estimate) | C7: 2020 [YR2020] | D7: 10.842
A8: Nigeria | B8: Unemployment, youth total (% of total labor force ages 15-24) (modeled ILO estimate) | C8: 2021 [YR2021] | D8: 8.991
A9: Nigeria | B9: Unemployment, youth total (% of total labor force ages 15-24) (modeled ILO estimate) | C9: 2022 [YR2022] | D9: 6.024
A10: Nigeria | B10: Unemployment, youth total (% of total labor force ages 15-24) (modeled ILO estimate) | C10: 2023 [YR2023] | D10: 5.131
A11: Nigeria | B11: Individuals using the Internet (% of population) | C11: 2015 [YR2015] | D11: 22.5142
A12: Nigeria | B12: Individuals using the Internet (% of population) | C12: 2016 [YR2016] | D12: 24.137501
A13: Nigeria | B13: Individuals using the Internet (% of population) | C13: 2017 [YR2017] | D13: 25.877899
... A253: Cote d'Ivoire | B253: Individuals using the Internet (% of population) | C253: 2023 [YR2023] | D253: 40.65285

Sheet PivotAnalysis
A1: Country Name | B1: Senegal
A3: Average of Value | B3: Column Labels
A4: Row Labels | B4: Individuals using the Internet (% of population) | C4: Unemployment, youth total (% of total labor force ages 15-24) (modeled ILO estimate) | D4: Grand Total
A5: 2015 [YR2015] | B5: 21.700001 | C5: 8.045 | D5: 14.8725
A6: 2016 [YR2016] | B6: 25.664801 | C6: 6.374 | D6: 16.0194
A7: 2017 [YR2017] | B7: 29.643101 | C7: 5.836 | D7: 17.73955
A8: 2018 [YR2018] | B8: 35.299999 | C8: 4.92 | D8: 20.11
A9: 2019 [YR2019] | B9: 43.3797 | C9: 4.037 | D9: 23.70835
A10: 2020 [YR2020] | B10: 53.3088 | C10: 4.817 | D10: 29.0629
A11: 2021 [YR2021] | B11: 55.040401 | C11: 4.661 | D11: 29.850701
A12: 2022 [YR2022] | B12: 56.8283 | C12: 3.902 | D12: 30.36515
A13: 2023 [YR2023] | B13: 59.187401 | C13: 3.859 | D13: 31.5232
A14: Grand Total | B14: 42.228056 | C14: 5.1612222 | D14: 23.694639

Sheet Summary
A1: Country | B1: Youth Unemployement 2023 | C1: Internet Users (2023
A2: Nigeria | B2: =ROUND(AVERAGEIFS(RawData!K:K, RawData!A:A, Summary!A2, RawData!B:B, "Unemployment*"), 1) -> 5.1 | C2: =ROUND(AVERAGEIFS(RawData!K:K, RawData!A:A, Summary!A2, RawData!B:B, "Individuals*"), 1) -> 40.1
A3: Malawi | B3: =ROUND(AVERAGEIFS(RawData!K:K, RawData!A:A, Summary!A3, RawData!B:B, "Unemployment*"), 1) -> 6.8 | C3: =ROUND(AVERAGEIFS(RawData!K:K, RawData!A:A, Summary!A3, RawData!B:B, "Individuals*"), 1) -> 18
A4: Mozambique | B4: =ROUND(AVERAGEIFS(RawData!K:K, RawData!A:A, Summary!A4, RawData!B:B, "Unemployment*"), 1) -> 11.5 | C4: =ROUND(AVERAGEIFS(RawData!K:K, RawData!A:A, Summary!A4, RawData!B:B, "Individuals*"), 1) -> 19.9
A5: Kenya | B5: =ROUND(AVERAGEIFS(RawData!K:K, RawData!A:A, Summary!A5, RawData!B:B, "Unemployment*"), 1) -> 15.2 | C5: =ROUND(AVERAGEIFS(RawData!K:K, RawData!A:A, Summary!A5, RawData!B:B, "Individuals*"), 1) -> 32.1
A6: Rwanda | B6: =ROUND(AVERAGEIFS(RawData!K:K, RawData!A:A, Summary!A6, RawData!B:B, "Unemployment*"), 1) -> 18.2 | C6: =ROUND(AVERAGEIFS(RawData!K:K, RawData!A:A, Summary!A6, RawData!B:B, "Individuals*"), 1) -> 28.8
A7: Ghana | B7: =ROUND(AVERAGEIFS(RawData!K:K, RawData!A:A, Summary!A7, RawData!B:B, "Unemployment*"), 1) -> 5.4 | C7: =ROUND(AVERAGEIFS(RawData!K:K, RawData!A:A, Summary!A7, RawData!B:B, "Individuals*"), 1) -> 70.7
A8: Egypt, Arab Rep. | B8: =ROUND(AVERAGEIFS(RawData!K:K, RawData!A:A, Summary!A8, RawData!B:B, "Unemployment*"), 1) -> 17.2 | C8: =ROUND(AVERAGEIFS(RawData!K:K, RawData!A:A, Summary!A8, RawData!B:B, "Individuals*"), 1) -> 74
A9: Tanzania | B9: =ROUND(AVERAGEIFS(RawData!K:K, RawData!A:A, Summary!A9, RawData!B:B, "Unemployment*"), 1) -> 2.3 | C9: =ROUND(AVERAGEIFS(RawData!K:K, RawData!A:A, Summary!A9, RawData!B:B, "Individuals*"), 1) -> 28.4
A10: Ethiopia | B10: =ROUND(AVERAGEIFS(RawData!K:K, RawData!A:A, Summary!A10, RawData!B:B, "Unemployment*"), 1) -> 5.5 | C10: =ROUND(AVERAGEIFS(RawData!K:K, RawData!A:A, Summary!A10, RawData!B:B, "Individuals*"), 1) -> 20.3
A11: Uganda | B11: =ROUND(AVERAGEIFS(RawData!K:K, RawData!A:A, Summary!A11, RawData!B:B, "Unemployment*"), 1) -> 4.2 | C11: =ROUND(AVERAGEIFS(RawData!K:K, RawData!A:A, Summary!A11, RawData!B:B, "Individuals*"), 1) -> 9.3
A12: Zambia | B12: =ROUND(AVERAGEIFS(RawData!K:K, RawData!A:A, Summary!A12, RawData!B:B, "Unemployment*"), 1) -> 10 | C12: =ROUND(AVERAGEIFS(RawData!K:K, RawData!A:A, Summary!A12, RawData!B:B, "Individuals*"), 1) -> 16.5
A13: Senegal | B13: =ROUND(AVERAGEIFS(RawData!K:K, RawData!A:A, Summary!A13, RawData!B:B, "Unemployment*"), 1) -> 3.9 | C13: =ROUND(AVERAGEIFS(RawData!K:K, RawData!A:A, Summary!A13, RawData!B:B, "Individuals*"), 1) -> 59.2
... A15: Cote d'Ivoire | B15: =ROUND(AVERAGEIFS(RawData!K:K, RawData!A:A, Summary!A15, RawData!B:B, "Unemployment*"), 1) -> 4.2 | C15: =ROUND(AVERAGEIFS(RawData!K:K, RawData!A:A, Summary!A15, RawData!B:B, "Individuals*"), 1) -> 40.7
A18: 2015 | B18: 2016 | C18: 2017 | D18: 2018 | E18: 2019 | F18: 2020 | G18: 2021 | H18: 2022 | I18: 2023
A19: =ROUND(AVERAGEIF(RawData!$B:$B, "Unemployment*", RawData!E:E), 1) -> 9.1 | B19: =ROUND(AVERAGEIF(RawData!$B:$B, "Unemployment*", RawData!F:F), 1) -> 8.7 | C19: =ROUND(AVERAGEIF(RawData!$B:$B, "Unemployment*", RawData!G:G), 1) -> 8.4 | D19: =ROUND(AVERAGEIF(RawData!$B:$B, "Unemployment*", RawData!H:H), 1) -> 9 | E19: =ROUND(AVERAGEIF(RawData!$B:$B, "Unemployment*", RawData!I:I), 1) -> 9 | F19: =ROUND(AVERAGEIF(RawData!$B:$B, "Unemployment*", RawData!J:J), 1) -> 8.6 | G19: =ROUND(AVERAGEIF(RawData!$B:$B, "Unemployment*", RawData!K:K), 1) -> 8.3 | H19: =ROUND(AVERAGEIF(RawData!$B:$B, "Unemployment*", RawData!J:J), 1) -> 8.6 | I19: =ROUND(AVERAGEIF(RawData!$B:$B, "Unemployment*", RawData!K:K), 1) -> 8.3

Sheet Dashboard
A1: Youth Employment & Digital Access in Africa (2023)
A3: 2023 YOUTH UNEMPLOYEMENT TRENDS IN AFRICA STATIC CHART ANALYSIS | P3: OVERALL YOUTH UNPLOYEMENT TRENDS IN AFRICA LIVE ANALYSIS
A4: Average Youth Unemployment
A5: =ROUND(AVERAGE(Summary!B2:B15), 1)&"%" -> 8.3%
A7: Average Internet Users
A8: =ROUND(AVERAGE(Summary!C2:C15), 1)&"%" -> 35.7%
A10: Highest Youth Unemployment
A11: =INDEX(Summary!A2:A15, MATCH(MAX(Summary!B2:B15), Summary!B2:B15, 0))&" ("&ROUND(MAX(Summary!B2:B15), 1)&"%)" -> Rwanda (18.2%)
A18: YOUTH UNEMPLOYEMENT VS INTERNET USAGE 2023

Sheet Series - Metadata
A1: Code | B1: License Type | C1: Indicator Name | D1: Long definition | E1: Source | F1: Topic | G1: Dataset | H1: Unit of measure | I1: Periodicity | J1: Reference period | K1: Aggregation method | L1: Statistical concept and methodology | M1: Development relevance | N1: Limitations and exceptions | O1: Other notes | P1: License URL
A2: SL.UEM.1524.ZS | B2: CC BY-4.0 | C2: Unemployment, youth total (% of total labor force ages 15-24) (modeled ILO estimate) | D2: Youth unemployment refers to the share of the labor force ages 15-24 without work but available for and seeking employment. | E2: ILO Modelled Estimates database (ILOEST), International Labour Organization (ILO), uri: https://ilostat.ilo.org/data/bulk/, publisher: ILOSTAT, type: external database, date accessed: January 17, 2026 | F2: Social Protection & Labor: Unemployment | G2: WB_WDI | H2: % of total labor force ages 15-24 | I2: Annual | J2: 1991-2025 | K2: Weighted average | L2: Methodology: The unemployment rate is calculated by expressing the number of unemployed persons as a percentage of the total number of persons in the labor force. The labor force (formerly known as the economically active population) is the sum of the number of persons employed and the number of persons unemployed. The series is part of the "ILO modeled estimates database," including nationally reported observations and imputed data for countries with missing data, primarily to capture regional and global trends with consistent country coverage. Country-reported microdata is based mainly on nationally representative labor force surveys, with other sources (e.g., household surveys and population censuses) considering differences in the data source, the scope of coverage, methodology, and other country-specific factors. Country analysis requires caution where limited nationally reported data are available. A series of models are also applied to impute missing observations and make projections. However, imputed observations are not based on national data, are subject to high uncertainty, and should not be used for country comparisons or rankings. For more information: https://ilostat.ilo.org/resources/concepts-and-definitions/ilo-modelled-estimates/ Statistical concept(s): The unemployed comprise all persons of working age who were: a) without work during the reference period, i.e. were not in paid employment or self-employment; b) currently available for work, i.e. were available for paid employment or self-employment during the reference period; and c) seeking work, i.e. had taken specific steps in a specified recent period to seek paid employment or self-employment. Future starters, that is, persons who did not look for work but have a future labor market stake (made arrangements for a future job start) are also counted as unemployed, as are participants in skills training or retraining schemes within employment promotion programs, who on that basis, were “not in employment”, not “currently available” and did not “seek employment” because they had a job offer to start within a short subsequent period generally not greater than three months. The unemployed also include persons “not in employment” who carried out activities to migrate abroad in order to work for pay or profit but who were still waiting for the opportunity to leave. Employment comprises all persons of working age who during a specified brief period, such as one week or one day, were in the following categories: a) paid employment (whether at work or with a job but not at work); or b) self-employment (whether at work or with an enterprise but not at work). The working-age population is the population above the legal working age, but for statistical purposes it comprises all persons above a specified minimum age threshold for which an inquiry on economic activity is made. To promote international comparability, the working-age population is often defined as all persons aged 15 and older, but this may vary from country to country based on national laws and practices (some countries also apply an upper age limit). | M2: The unemployment rate is a useful measure of the underutilization of the labor supply. It reflects the inability of an economy to generate employment for those persons who want to work but are not doing so, even though they are available for employment and actively seeking work. It is thus seen as an indicator of the efficiency and effectiveness of an economy to absorb its labor force and of the performance of the labor market. Given its usefulness in conveying valuable information on a country’s labor market situation and the fact that it is widely recognized as a headline labor market indicator, it was included as one of the indicators to measure progress towards the achievement of the Sustainable Development Goals (SDG), under Goal 8 (Promote sustained, inclusive and sustainable economic growth, full and productive employment and decent work for all). Youth unemployment is an important policy issue for many economies. Young men and women today face increasing uncertainty in their hopes of undergoing a satisfactory transition in the labour market, and this uncertainty and disillusionment can, in turn, have damaging effects on individuals, communities, economies and society at large. Unemployed or underemployed youth are less able to contribute effectively to national development and have fewer opportunities to exercise their rights as citizens. They have less to spend as consumers, less to invest as savers and often have no "voice" to bring about change in their lives and communities. Widespread youth unemployment and underemployment also prevents companies and countries from innovating and developing competitive advantages based on human capital investment, thus undermining future prospects. | N2: The criteria for people considered to be seeking work, and the treatment of people temporarily laid off or seeking work for the first time, vary across countries. In many cases it is especially difficult to measure employment and unemployment in agriculture. The timing of a survey can maximize the effects of seasonal unemployment in agriculture. And informal sector employment is difficult to quantify where informal activities are not tracked. There may be also persons not currently in the labour market who want to work but do not actively "seek" work because they view job opportunities as limited, or because they have restricted labour mobility, or face discrimination, or structural, social or cultural barriers. The exclusion of people who want to work but are not seeking work (often called the "hidden unemployed" or "discouraged workers") is a criterion that will affect the unemployment count of both women and men. However, women tend to be excluded from the count for various reasons. Women suffer more from discrimination and from structural, social, and cultural barriers that impede them from seeking work. Also, women are often responsible for the care of children and the elderly and for household affairs. They may not be available for work during the short reference period, as they need to make arrangements before starting work. Further, women are considered to be employed when they are working part-time or in temporary jobs, despite the instability of these jobs or their active search for more secure employment. | O2: National estimates are also available in the WDI database. Caution should be used when comparing ILO estimates with national estimates. | P2: https://datacatalog.worldbank.org/int/public-licenses#cc-by
A3: IT.NET.USER.ZS | B3: CC BY-4.0 | C3: Individuals using the Internet (% of population) | D3: Internet users are individuals who have used the Internet (from any location) in the last 3 months. The Internet can be used via a computer, mobile phone, personal digital assistant, games machine, digital TV etc. | E3: World Telecommunication/ICT Indicators Database, International Telecommunication Union (ITU), uri: https://datahub.itu.int/ | F3: Infrastructure: Communications | G3: WB_WDI | H3: % of population | I3: Annual | J3: 1990-2025 | K3: Weighted average | L3: Methodology: The Internet is a world-wide public computer network. It provides access to a number of communication services including the World Wide Web and carries email, news, entertainment and data files, irrespective of the device used (not assumed to be only via a computer - it may also be by mobile phone, PDA, games machine, digital TV etc.). Access can be via a fixed or mobile network. For additional/latest information on sources and country notes, please also refer to: https://www.itu.int/en/ITU-D/Statistics/Pages/stat/default.aspx Statistical concept(s): The number of in-scope individuals using the Internet is calculated by aggregating the weighted responses. The proportion of individuals using the Internet is expressed as a percentage and is calculated by dividing the total number of in-scope individuals using the Internet by the total number of in-scope individuals, and then multiplying the result by 100. | M3: The digital and information revolution has changed the way the world learns, communicates, does business, and treats illnesses. New information and communications technologies (ICT) offer vast opportunities for progress in all walks of life in all countries - opportunities for economic growth, improved health, better service delivery, learning through distance education, and social and cultural advances. Today's smartphones and tablets have computer power equivalent to that of yesterday's computers and provide a similar range of functions. Device convergence is thus rendering the conventional definition obsolete. Comparable statistics on access, use, quality, and affordability of ICT are needed to formulate growth-enabling policies for the sector and to monitor and evaluate the sector's impact on development. Although basic access data are available for many countries, in most developing countries little is known about who uses ICT; what they are used for (school, work, business, research, government); and how they affect people and businesses. The global Partnership on Measuring ICT for Development is helping to set standards, harmonize information and communications technology statistics, and build statistical capacity in developing countries. However, despite significant improvements in the developing world, the gap between the ICT haves and have-nots remains. | N3: Operators have traditionally been the main source of telecommunications data, so information on subscriptions has been widely available for most countries. This gives a general idea of access, but a more precise measure is the penetration rate - the share of households with access to telecommunications. During the past few years more information on information and communication technology use has become available from household and business surveys. Also important are data on actual use of telecommunications services. Ideally, statistics on telecommunications (and other information and communications technologies) should be compiled for all three measures: subscriptions, access, and use. The quality of data varies among reporting countries as a result of differences in regulations covering data provision and availability. Discrepancies may also arise in cases where the end of a fiscal year differs from that used by ITU, which is the end of December of every year. A number of countries have fiscal years that end in March or June of every year. | O3: Please cite the International Telecommunication Union for third-party use of these data. | P3: https://datacatalog.worldbank.org/int/public-licenses#cc-by
